{
    "fluentMethods": true,
    "relationships": [
        {
            "relationshipType": "one-to-many",
            "relationshipName": "ville",
            "otherEntityName": "ville",
            "otherEntityRelationshipName": "site"
        },
        {
            "relationshipType": "many-to-many",
            "relationshipName": "parcours",
            "otherEntityName": "parcours",
            "ownerSide": false,
            "otherEntityRelationshipName": "site"
        }
    ],
    "fields": [
        {
            "fieldName": "nom",
            "fieldType": "String"
        },
        {
            "fieldName": "lienUrl",
            "fieldType": "String"
        },
        {
            "fieldName": "prix",
            "fieldType": "Long"
        },
        {
            "fieldName": "description",
            "fieldType": "String"
        },
        {
            "fieldName": "adresse",
            "fieldType": "String"
        }
    ],
    "changelogDate": "20171026120406",
    "entityTableName": "site",
    "dto": "no",
    "pagination": "no",
    "service": "serviceImpl",
    "jpaMetamodelFiltering": false
}